AUTHORS
LICENSE
MANIFEST.in
README.rst
setup.cfg
setup.py
django_cbtools/__init__.py
django_cbtools/connection.py
django_cbtools/models.py
django_cbtools/sync_gateway.py
django_cbtools/tests.py
django_cbtools/views.py
django_cbtools.egg-info/PKG-INFO
django_cbtools.egg-info/SOURCES.txt
django_cbtools.egg-info/dependency_links.txt
django_cbtools.egg-info/pbr.json
django_cbtools.egg-info/requires.txt
django_cbtools.egg-info/top_level.txt
django_cbtools/couchbase_views/by_channel.js
django_cbtools/couchbase_views/by_type.js
django_cbtools/couchbase_views/deleted_documents.js
django_cbtools/management/__init__.py
django_cbtools/management/commands/__init__.py
django_cbtools/management/commands/clear_st_deleted.py
django_cbtools/management/commands/create_cb_views.py
django_cbtools/management/commands/create_sg_users.py
docs/Makefile
docs/conf.py
docs/index.rst
docs/installation.rst
docs/settings.rst
docs/tutorial.rst