Metadata-Version: 1.1
Name: django-cbtools
Version: 1.2.0
Summary: Simple models and views to work with Couchbase in Django applications.
Home-page: https://github.com/smarttradeapp/django_cbtools
Author: Viacheslav Iutin
Author-email: slava@smarttradeapp.com
License: MIT
Keywords: couchbase django sync-gateway
Platform: UNKNOWN
Classifier: Development Status :: 4 - Beta
Classifier: Framework :: Django
Classifier: Operating System :: OS Independent
Classifier: Intended Audience :: Developers
Classifier: Topic :: Utilities
Classifier: License :: OSI Approved :: MIT License
Classifier: Programming Language :: Python
Classifier: Programming Language :: Python :: 2
Classifier: Programming Language :: Python :: 3
